PerspectiveLearning/PerspectiveLearning.py
PerspectiveLearning/__init__.py
perspectivelearning-0.1.3.dist-info/LICENSE
perspectivelearning-0.1.3.dist-info/METADATA
perspectivelearning-0.1.3.dist-info/WHEEL
perspectivelearning-0.1.3.dist-info/top_level.txt
perspectivelearning-0.1.3.dist-info/RECORD
