Metadata-Version: 2.1
Name: perspectivelearning
Version: 0.1.3
Summary: A dynamic framework for hypothesis-driven iterative machine learning.
Author: Sai Pavan Velidandla
Author-email: connectwithpavan@gmail.com
Classifier: Programming Language :: Python :: 3
Classifier: License :: OSI Approved :: MIT License
Classifier: Operating System :: OS Independent
Requires-Python: >=3.7
License-File: LICENSE
Requires-Dist: numpy
Requires-Dist: pandas
Requires-Dist: scikit-learn
